<xml>
  <block type="lsystem_symbol_def" x="8" y="45">
    <title name="NAME">A</title>
    <statement name="RULES">
      <block type="lsystem_symbol_ref">
        <title name="SYMBOL">B</title>
        <next>
          <block type="lsystem_branch">
            <statement name="RULE">
              <block type="lsystem_rotate_axis" inline="false">
                <title name="AXIS">X</title>
                <value name="ANGLE">
                  <block type="math_number">
                    <title name="NUM">30</title>
                  </block>
                </value>
                <next>
                  <block type="lsystem_symbol_ref">
                    <title name="SYMBOL">A</title>
                  </block>
                </next>
              </block>
            </statement>
            <next>
              <block type="lsystem_rotate_axis" inline="false">
                <title name="AXIS">Y</title>
                <value name="ANGLE">
                  <block type="math_number">
                    <title name="NUM">136</title>
                  </block>
                </value>
                <next>
                  <block type="lsystem_symbol_ref">
                    <title name="SYMBOL">A</title>
                  </block>
                </next>
              </block>
            </next>
          </block>
        </next>
      </block>
    </statement>
    <statement name="VISUALS">
      <block type="visualize_line" inline="false">
        <title name="COLOR">#ffcc99</title>
      </block>
    </statement>
    <next>
      <block type="lsystem_symbol_def">
        <title name="NAME">B</title>
        <statement name="RULES">
          <block type="lsystem_rotate_axis" inline="false">
            <title name="AXIS">Y</title>
            <value name="ANGLE">
              <block type="math_number">
                <title name="NUM">120</title>
              </block>
            </value>
            <next>
              <block type="lsystem_symbol_ref">
                <title name="SYMBOL">C</title>
              </block>
            </next>
          </block>
        </statement>
        <statement name="VISUALS">
          <block type="visualize_line" inline="false">
            <title name="COLOR">#99ffcc</title>
          </block>
        </statement>
        <next>
          <block type="lsystem_symbol_def">
            <title name="NAME">C</title>
            <statement name="RULES">
              <block type="lsystem_symbol_ref">
                <title name="SYMBOL">C</title>
              </block>
            </statement>
            <statement name="VISUALS">
              <block type="visualize_line" inline="false">
                <title name="COLOR">#99ccff</title>
              </block>
            </statement>
            <next>
              <block type="lsystem_init">
                <title name="STEPS">6</title>
                <statement name="INIT_STATE">
                  <block type="lsystem_symbol_ref">
                    <title name="SYMBOL">A</title>
                  </block>
                </statement>
              </block>
            </next>
          </block>
        </next>
      </block>
    </next>
  </block>
</xml>
